{
  "schema": "IFC2X3",
  "embedding_model": "BAAI/bge-m3",
  "embedding_dim": 1024,
  "profile_version": "v001",
  "ontology_content_hash": "71fb9453ff4fc0dffe2b5526a717b6d578db2b811b49197da7a78045d4db899c",
  "count": 301,
  "ifc_classes": [
    "IfcActionRequest",
    "IfcActor",
    "IfcActuatorType",
    "IfcAirTerminalBoxType",
    "IfcAirTerminalType",
    "IfcAirToAirHeatRecoveryType",
    "IfcAlarmType",
    "IfcAnnotation",
    "IfcAsset",
    "IfcBeam",
    "IfcBeamType",
    "IfcBoilerType",
    "IfcBuilding",
    "IfcBuildingElement",
    "IfcBuildingElementComponent",
    "IfcBuildingElementPart",
    "IfcBuildingElementProxy",
    "IfcBuildingElementProxyType",
    "IfcBuildingElementType",
    "IfcBuildingStorey",
    "IfcCableCarrierFittingType",
    "IfcCableCarrierSegmentType",
    "IfcCableSegmentType",
    "IfcChamferEdgeFeature",
    "IfcChillerType",
    "IfcCoilType",
    "IfcColumn",
    "IfcColumnType",
    "IfcCompressorType",
    "IfcCondenserType",
    "IfcCondition",
    "IfcConditionCriterion",
    "IfcConstructionEquipmentResource",
    "IfcConstructionMaterialResource",
    "IfcConstructionProductResource",
    "IfcConstructionResource",
    "IfcControl",
    "IfcControllerType",
    "IfcCooledBeamType",
    "IfcCoolingTowerType",
    "IfcCostItem",
    "IfcCostSchedule",
    "IfcCovering",
    "IfcCoveringType",
    "IfcCrewResource",
    "IfcCurtainWall",
    "IfcCurtainWallType",
    "IfcDamperType",
    "IfcDiscreteAccessory",
    "IfcDiscreteAccessoryType",
    "IfcDistributionChamberElement",
    "IfcDistributionChamberElementType",
    "IfcDistributionControlElement",
    "IfcDistributionControlElementType",
    "IfcDistributionElement",
    "IfcDistributionElementType",
    "IfcDistributionFlowElement",
    "IfcDistributionFlowElementType",
    "IfcDistributionPort",
    "IfcDoor",
    "IfcDoorLiningProperties",
    "IfcDoorPanelProperties",
    "IfcDoorStyle",
    "IfcDuctFittingType",
    "IfcDuctSegmentType",
    "IfcDuctSilencerType",
    "IfcEdgeFeature",
    "IfcElectricApplianceType",
    "IfcElectricDistributionPoint",
    "IfcElectricFlowStorageDeviceType",
    "IfcElectricGeneratorType",
    "IfcElectricHeaterType",
    "IfcElectricMotorType",
    "IfcElectricTimeControlType",
    "IfcElectricalBaseProperties",
    "IfcElectricalCircuit",
    "IfcElectricalElement",
    "IfcElement",
    "IfcElementAssembly",
    "IfcElementComponent",
    "IfcElementComponentType",
    "IfcElementQuantity",
    "IfcElementType",
    "IfcEnergyConversionDevice",
    "IfcEnergyConversionDeviceType",
    "IfcEnergyProperties",
    "IfcEquipmentElement",
    "IfcEquipmentStandard",
    "IfcEvaporativeCoolerType",
    "IfcEvaporatorType",
    "IfcFanType",
    "IfcFastener",
    "IfcFastenerType",
    "IfcFeatureElement",
    "IfcFeatureElementAddition",
    "IfcFeatureElementSubtraction",
    "IfcFilterType",
    "IfcFireSuppressionTerminalType",
    "IfcFlowController",
    "IfcFlowControllerType",
    "IfcFlowFitting",
    "IfcFlowFittingType",
    "IfcFlowInstrumentType",
    "IfcFlowMeterType",
    "IfcFlowMovingDevice",
    "IfcFlowMovingDeviceType",
    "IfcFlowSegment",
    "IfcFlowSegmentType",
    "IfcFlowStorageDevice",
    "IfcFlowStorageDeviceType",
    "IfcFlowTerminal",
    "IfcFlowTerminalType",
    "IfcFlowTreatmentDevice",
    "IfcFlowTreatmentDeviceType",
    "IfcFluidFlowProperties",
    "IfcFooting",
    "IfcFurnishingElement",
    "IfcFurnishingElementType",
    "IfcFurnitureStandard",
    "IfcFurnitureType",
    "IfcGasTerminalType",
    "IfcGrid",
    "IfcGroup",
    "IfcHeatExchangerType",
    "IfcHumidifierType",
    "IfcInventory",
    "IfcJunctionBoxType",
    "IfcLaborResource",
    "IfcLampType",
    "IfcLightFixtureType",
    "IfcMechanicalFastener",
    "IfcMechanicalFastenerType",
    "IfcMember",
    "IfcMemberType",
    "IfcMotorConnectionType",
    "IfcMove",
    "IfcObject",
    "IfcObjectDefinition",
    "IfcOccupant",
    "IfcOpeningElement",
    "IfcOrderAction",
    "IfcOutletType",
    "IfcPerformanceHistory",
    "IfcPermeableCoveringProperties",
    "IfcPermit",
    "IfcPile",
    "IfcPipeFittingType",
    "IfcPipeSegmentType",
    "IfcPlate",
    "IfcPlateType",
    "IfcPort",
    "IfcProcedure",
    "IfcProcess",
    "IfcProduct",
    "IfcProject",
    "IfcProjectOrder",
    "IfcProjectOrderRecord",
    "IfcProjectionElement",
    "IfcPropertyDefinition",
    "IfcPropertySet",
    "IfcPropertySetDefinition",
    "IfcProtectiveDeviceType",
    "IfcProxy",
    "IfcPumpType",
    "IfcRailing",
    "IfcRailingType",
    "IfcRamp",
    "IfcRampFlight",
    "IfcRampFlightType",
    "IfcReinforcementDefinitionProperties",
    "IfcReinforcingBar",
    "IfcReinforcingElement",
    "IfcReinforcingMesh",
    "IfcRelAggregates",
    "IfcRelAssigns",
    "IfcRelAssignsTasks",
    "IfcRelAssignsToActor",
    "IfcRelAssignsToControl",
    "IfcRelAssignsToGroup",
    "IfcRelAssignsToProcess",
    "IfcRelAssignsToProduct",
    "IfcRelAssignsToProjectOrder",
    "IfcRelAssignsToResource",
    "IfcRelAssociates",
    "IfcRelAssociatesAppliedValue",
    "IfcRelAssociatesApproval",
    "IfcRelAssociatesClassification",
    "IfcRelAssociatesConstraint",
    "IfcRelAssociatesDocument",
    "IfcRelAssociatesLibrary",
    "IfcRelAssociatesMaterial",
    "IfcRelAssociatesProfileProperties",
    "IfcRelConnects",
    "IfcRelConnectsElements",
    "IfcRelConnectsPathElements",
    "IfcRelConnectsPortToElement",
    "IfcRelConnectsPorts",
    "IfcRelConnectsStructuralActivity",
    "IfcRelConnectsStructuralElement",
    "IfcRelConnectsStructuralMember",
    "IfcRelConnectsWithEccentricity",
    "IfcRelConnectsWithRealizingElements",
    "IfcRelContainedInSpatialStructure",
    "IfcRelCoversBldgElements",
    "IfcRelCoversSpaces",
    "IfcRelDecomposes",
    "IfcRelDefines",
    "IfcRelDefinesByProperties",
    "IfcRelDefinesByType",
    "IfcRelFillsElement",
    "IfcRelFlowControlElements",
    "IfcRelInteractionRequirements",
    "IfcRelNests",
    "IfcRelOccupiesSpaces",
    "IfcRelOverridesProperties",
    "IfcRelProjectsElement",
    "IfcRelReferencedInSpatialStructure",
    "IfcRelSchedulesCostItems",
    "IfcRelSequence",
    "IfcRelServicesBuildings",
    "IfcRelSpaceBoundary",
    "IfcRelVoidsElement",
    "IfcRelationship",
    "IfcResource",
    "IfcRoof",
    "IfcRoot",
    "IfcRoundedEdgeFeature",
    "IfcSanitaryTerminalType",
    "IfcScheduleTimeControl",
    "IfcSensorType",
    "IfcServiceLife",
    "IfcServiceLifeFactor",
    "IfcSite",
    "IfcSlab",
    "IfcSlabType",
    "IfcSoundProperties",
    "IfcSoundValue",
    "IfcSpace",
    "IfcSpaceHeaterType",
    "IfcSpaceProgram",
    "IfcSpaceThermalLoadProperties",
    "IfcSpaceType",
    "IfcSpatialStructureElement",
    "IfcSpatialStructureElementType",
    "IfcStackTerminalType",
    "IfcStair",
    "IfcStairFlight",
    "IfcStairFlightType",
    "IfcStructuralAction",
    "IfcStructuralActivity",
    "IfcStructuralAnalysisModel",
    "IfcStructuralConnection",
    "IfcStructuralCurveConnection",
    "IfcStructuralCurveMember",
    "IfcStructuralCurveMemberVarying",
    "IfcStructuralItem",
    "IfcStructuralLinearAction",
    "IfcStructuralLinearActionVarying",
    "IfcStructuralLoadGroup",
    "IfcStructuralMember",
    "IfcStructuralPlanarAction",
    "IfcStructuralPlanarActionVarying",
    "IfcStructuralPointAction",
    "IfcStructuralPointConnection",
    "IfcStructuralPointReaction",
    "IfcStructuralReaction",
    "IfcStructuralResultGroup",
    "IfcStructuralSurfaceConnection",
    "IfcStructuralSurfaceMember",
    "IfcStructuralSurfaceMemberVarying",
    "IfcSubContractResource",
    "IfcSwitchingDeviceType",
    "IfcSystem",
    "IfcSystemFurnitureElementType",
    "IfcTankType",
    "IfcTask",
    "IfcTendon",
    "IfcTendonAnchor",
    "IfcTimeSeriesSchedule",
    "IfcTransformerType",
    "IfcTransportElement",
    "IfcTransportElementType",
    "IfcTubeBundleType",
    "IfcTypeObject",
    "IfcTypeProduct",
    "IfcUnitaryEquipmentType",
    "IfcValveType",
    "IfcVibrationIsolatorType",
    "IfcVirtualElement",
    "IfcWall",
    "IfcWallStandardCase",
    "IfcWallType",
    "IfcWasteTerminalType",
    "IfcWindow",
    "IfcWindowLiningProperties",
    "IfcWindowPanelProperties",
    "IfcWindowStyle",
    "IfcWorkControl",
    "IfcWorkPlan",
    "IfcWorkSchedule",
    "IfcZone"
  ]
}
